aiohttp_asgi_connector-1.1.1.dist-info/METADATA
aiohttp_asgi_connector-1.1.1.dist-info/WHEEL
aiohttp_asgi_connector-1.1.1.dist-info/entry_points.txt
aiohttp_asgi_connector-1.1.1.dist-info/licenses/LICENSE
aiohttp_asgi_connector/__init__.py
aiohttp_asgi_connector/connector.py
aiohttp_asgi_connector/py.typed
aiohttp_asgi_connector/transport.py
aiohttp_asgi_connector-1.1.1.dist-info/RECORD
