Metadata-Version: 2.1
Name: aiohttp-asgi-connector
Version: 1.1.1
Summary: AIOHTTP Connector for running ASGI applications
Keywords: fastapi,aiohttp,asgi,testing,starlette,httpx,asyncio
Author-Email: thearchitector <me@eliasfgabriel.com>
License: BSD-3-Clause
Requires-Python: >=3.8
Requires-Dist: aiohttp>=3.1.0; python_version >= "3.9"
Requires-Dist: aiohttp<3.11,>=3.1.0; python_version ~= "3.8.0"
